<?xml version="1.0"?>
<psalm
    errorLevel="8"
    resolveFromConfigFile="true"
    reportMixedIssues="false"
    useDocblockTypes="false"
    useDocblockPropertyTypes="false"
    xmlns:xsi="http://www.w3.org/2001/XMLSchema-instance"
    xmlns="https://getpsalm.org/schema/config"
    xsi:schemaLocation="https://getpsalm.org/schema/config vendor/vimeo/psalm/config.xsd"
    autoloader="tests/phpstan/phpstan_bootstrap.php"
>
    <issueHandlers>
        <UndefinedDocblockClass errorLevel="suppress" />
    </issueHandlers>
    <projectFiles>
        <directory name="application/" />
        <ignoreFiles>
            <directory name="vendor" />
            <directory name="third_party" />
            <directory name="application/views" />
            <directory name="application/tests" />
            <directory name="application/helpers/Zend" />
            <file name="application/libraries/simpletester.php" />
        </ignoreFiles>
    </projectFiles>
</psalm>
