{
  "survey": {
    "sid": 8,
    "gsid": 1,
    "active": false,
    "language": "en",
    "expires": null,
    "startDate": null,
    "anonymized": true,
    "saveTimings": false,
    "datestamp": true,
    "useCookie": false,
    "allowRegister": false,
    "allowSave": true,
    "autoNumberStart": 0,
    "autoRedirect": false,
    "allowPrev": true,
    "printAnswers": true,
    "ipAddr": false,
    "ipAnonymize": false,
    "refUrl": false,
    "dateCreated": "2023-05-23T06:55:12.000Z",
    "publicStatistics": true,
    "publicGraphs": false,
    "listPublic": true,
    "sendConfirmation": true,
    "tokenAnswersPersistence": false,
    "assessments": false,
    "useCaptcha": false,
    "useTokens": false,
    "bounceEmail": "admin.limesurvey@opensurvey.it",
    "attributeDescriptions": "",
    "emailResponseTo": "",
    "emailNotificationTo": "",
    "tokenLength": 15,
    "showXQuestions": true,
    "showGroupInfo": "B",
    "showNoAnswer": true,
    "showQNumCode": "B",
    "bounceTime": 0,
    "bounceProcessing": false,
    "bounceAccountType": "",
    "bounceAccountHost": "",
    "bounceAccountPass": "",
    "bounceAccountEncryption": "",
    "bounceAccountUser": "",
    "showWelcome": true,
    "showProgress": true,
    "questionIndex": 2,
    "navigationDelay": 0,
    "noKeyboard": false,
    "allowedItAfterCompletion": false,
    "googleAnalyticsStyle": 0,
    "googleAnalyticsApiKey": "",
    "showSurveyPolicyNotice": 0,
    "defaultLanguage": {
      "sid": 282267,
      "language": "en",
      "title": "Sample LimeSurvey EN\/FR\/DE\/IT (LS5)",
      "description": "This survey show all question type of LimeSurvey with some option",
      "welcomeText": "<p>This is the welcome text for the survey! You can can edit it in the survey properties.<\/p>\r\n",
      "endText": "<p>This is the end message for the survey! A good place to thank you to answer to this survey.<\/p>\r\n",
      "policyNotice": "",
      "policyError": "",
      "policyNoticeLabel": "",
      "url": "http:\/\/www.limesurvey.org",
      "urlDescription": "The end URL description of your survey. This URL can be automatically load when survey is completed.",
      "dateFormat": 5,
      "numberFormat": 0
    },
    "languageSettings": {
      "en": {
        "sid": 282267,
        "language": "en",
        "title": "Sample Empty LimeSurvey EN",
        "description": null,
        "welcomeText": null,
        "endText": null,
        "policyNotice": null,
        "policyError": null,
        "policyNoticeLabel": null,
        "url": null,
        "urlDescription": null,
        "dateFormat": 0,
        "numberFormat": 0
      }
    },
    "languages": [
      "en"
    ]
  }
}
